setup.cfg
setup.py
pyitachip2sl/__init__.py
pyitachip2sl.egg-info/PKG-INFO
pyitachip2sl.egg-info/SOURCES.txt
pyitachip2sl.egg-info/dependency_links.txt
pyitachip2sl.egg-info/top_level.txt
pyitachip2sl.egg-info/zip-safe