Metadata-Version: 1.1
Name: pyitachip2sl
Version: 0.1
Summary: Python API for sending commands via GlobalCache iTach IP to Serial device
Home-page: https://github.com/koolsb/pyitachip2sl
Author: Ben Kools
Author-email: koolsb@my.uwstout.edu
License: MIT
Download-URL: https://github.com/koolsb/pyitachip2sl/archive/0.1.tar.gz
Platform: UNKNOWN
Classifier: Development Status :: 4 - Beta
Classifier: Programming Language :: Python :: 3.5
